setup.py
youtube_cue/__init__.py
youtube_cue/musicbrainz.py
youtube_cue/youtube.py
youtube_cue.egg-info/PKG-INFO
youtube_cue.egg-info/SOURCES.txt
youtube_cue.egg-info/dependency_links.txt
youtube_cue.egg-info/entry_points.txt
youtube_cue.egg-info/requires.txt
youtube_cue.egg-info/top_level.txt